pileup_reads/__init__.py
pileup_reads/__main__.py
pileup_reads/bam_util.py
pileup_reads/check_util.py
pileup_reads/pileup_util.py
pileup_reads/run.py
pileup_reads/util.py
pileup_reads-0.0.1.dist-info/METADATA
pileup_reads-0.0.1.dist-info/WHEEL
pileup_reads-0.0.1.dist-info/licenses/LICENSE
pileup_reads-0.0.1.dist-info/RECORD
